django_password_rotate-1.0.2.dist-info/licenses/LICENSE
password_rotate/__init__.py
password_rotate/admin.py
password_rotate/apps.py
password_rotate/forms.py
password_rotate/managers.py
password_rotate/middleware.py
password_rotate/models.py
password_rotate/signals.py
password_rotate/urls.py
password_rotate/utils.py
password_rotate/validators.py
password_rotate/views.py
password_rotate/migrations/0001_initial.py
password_rotate/migrations/__init__.py
password_rotate/tests/__init__.py
password_rotate/tests/settings.py
password_rotate/tests/test_util.py
password_rotate/tests/urls.py
password_rotate/tests/utils.py
django_password_rotate-1.0.2.dist-info/METADATA
django_password_rotate-1.0.2.dist-info/WHEEL
django_password_rotate-1.0.2.dist-info/top_level.txt
django_password_rotate-1.0.2.dist-info/RECORD
