Metadata-Version: 2.4
Name: django-password-rotate
Version: 1.0.2
Summary: Django app for forcing password rotation
Home-page: https://github.com/alexandriagroup/django-password-rotate
Author: Taurus Olson
Author-email: taurusolson@gmail.com
License: BSD
Classifier: Environment :: Web Environment
Classifier: Framework :: Django
Classifier: Framework :: Django :: 4.2
Classifier: Development Status :: 5 - Production/Stable
Classifier: Intended Audience :: Developers
Classifier: License :: OSI Approved :: BSD License
Classifier: Operating System :: OS Independent
Classifier: Programming Language :: Python
Classifier: Programming Language :: Python :: 3
Classifier: Programming Language :: Python :: 3 :: Only
Requires-Python: >=3.8
License-File: LICENSE
Requires-Dist: Django>=4.2
Requires-Dist: humanize==4.10.0
Requires-Dist: rapidfuzz==3.9.7
Dynamic: license-file
